<?xml version="1.0" encoding="ISO-8859-1"?>
<entity-relation-data lastUpdate="2023-03-27 17:30:51" record="44193" source="Espacenet">
	<entities>
		<entity ref="Patent44193" type="Patent">
			<semanticIdentifier>brcris::091392e6ad167ddf91b0a8e4d2370da9</semanticIdentifier>
			<semanticIdentifier>docdb::BR102014023505A2</semanticIdentifier>
			<semanticIdentifier>epodoc::BR102014023505</semanticIdentifier>
			<semanticIdentifier>docdb::BR102014023505A</semanticIdentifier>
			<semanticIdentifier>epodoc::BR20141023505</semanticIdentifier>
			<semanticIdentifier>original::102014023505</semanticIdentifier>
			<field name="urlEspacenet" value="https://worldwide.espacenet.com/patent/search?q=102014023505"/>
			<field name="identifier.lattes" value="9443243894564249"/>
			<field name="identifier.espacenet" value="102014023505"/>
			<field name="kindCode" value="A2"/>
			<field name="title.espacenet" value="reator pirometalúrgico para escória líquida"/>
			<field name="title.lattes" value="Título sob sigilo"/>
			<field name="depositDate" value="2014-09-22"/>
			<field name="publicationDate" value="2017-09-26"/>
			<field name="countryCode" value="BR"/>
			<field name="inventor" value="AKIRA MIZOGUCHI"/>
			<field name="inventor" value="ANDRE ALEXANDRINO LOTTO"/>
			<field name="inventor" value="ANDRE LUIZ NUNIS DA SILVA"/>
			<field name="inventor" value="ANTONIO MALYNOWSKYJ"/>
			<field name="inventor" value="FABIANO FERREIRA CHOTOLI"/>
			<field name="inventor" value="JOAO BATISTA FERREIRA NETO"/>
			<field name="inventor" value="JOAO OSWALDO MACEDO GARCIA DE FARIA"/>
			<field name="inventor" value="TIAGO RAMOS RIBEIRO"/>
			<field name="inventor" value="VALDECIR ANGELO QUARCIONI"/>
			<field name="applicant" value="INSTITUTO DE PESQUISAS TECNOLOGICAS DE SAO PAULO S/A"/>
			<field name="applicant" value="INTERCEMENT BRASIL S.A"/>
			<field name="classification.ipc">
				<field name="sequence" value="1"/>
				<field name="text" value="C04B5/00AI"/>
				<field name="section" value="C"/>
				<field name="class" value="04"/>
				<field name="subclass" value="B"/>
				<field name="group" value="5"/>
				<field name="subgroup" value="00AI"/>
			</field>
			<field name="classification.ipc">
				<field name="sequence" value="2"/>
				<field name="text" value="C21B3/06AI"/>
				<field name="section" value="C"/>
				<field name="class" value="21"/>
				<field name="subclass" value="B"/>
				<field name="group" value="3"/>
				<field name="subgroup" value="06AI"/>
			</field>
			<field name="abstract.espacenet" value="reator pirometalúrgico para escória liquida, trata de um reator pirometalúrgico rotativo e basculante, pertencente aos campos da mecânica e da metalurgia, de uso para conter escória líquida para a adição de produtos, subprodutos e resíduos industriais, com vistas a proporcionar a mistura e homogeneização com a escória ainda liquida, constituído de um conjunto formado por uma plataforma dinãmica (1), um silo de dosagem (2) e pote de contenção (3). a plataforma dinãmica (1) é constituída de uma mesa (4) contendo central e lateralmente de eixos (5) que se apoiam em mancais (6) dispostos em colunas (7) fixadas sobre uma base estruturada (8); no perímetro ínfero-posterior da mesa (4) está fixado o eixo de um dispositivo de deslocamento linear (9), que, quando acionado, comprime o perímetro ínfero-posterior da mesa (4) para cima, de forma a incliná-la para a frente; no centro da mesa (4) está disposto um motoredutor (10), cujo eixo (11) está transversal e retangularmente posicionado em relação à mesa (4), sendo que sobre o eixo (11) está fixada uma estrutura (12), enquanto que nas proximidades do entorno do eixo (11) estão previstos roletes (13), cujas bases estão fixadas sobre a mesa (4) e cujas faces rolantes encostam-se a superfície inferior da estrutura (12); nos vértices da estrutura (12) estão dispostas colunas (14) de apoio, enquanto que em torno de sua base estão previstas duas ou mais fisgas retráteis (15), acionadas por dispositivo de deslocamento linear (16); sobre o centro da estrutura (12) é encaixado um reator cônico (17), contendo um ressalto anelar (18) em seu perímetro inferior e externo, eixos transversais (19) opostamente dispostos em seu perímetro superior e ranhuras (20) em torno de seu perímetro interno; o silo de dosagem (2) é constituído de uma estrutura vertical (21) dotada de um reservatório (22), cuja saída inferior culmina em uma rosca sem fim acoplada a motoredutor, que despeja o material para dentro de uma calha retrátil (23) direcionada para dentro do reator cônico (17), sendo a calha (23) movimentada por ação de um dispositivo de deslocamento linear; na lateral do silo de dosagem se projeta uma viga (24), cujo extremo apoia um dispositivo de deslocamento linear (25), que pode ser um pistão hidráulico ou pistão pneumático, dotado em seu extremo de sensor de temperatura (26); a plataforma dinãmica (1) é instalada ao lado de um fosso (27) dentro do qual é adicionado um pote de contenção (3)."/>
			<field name="originatesFrom" value="62027661"/>
			<field name="alternateIdentifier">
				<field name="status" value="Publication"/>
				<field name="format" value="docdb"/>
				<field name="country" value="BR"/>
				<field name="number" value="102014023505"/>
				<field name="kind" value="A2"/>
			</field>
			<field name="alternateIdentifier">
				<field name="status" value="Publication"/>
				<field name="format" value="epodoc"/>
				<field name="country" value="BR"/>
				<field name="number" value="BR102014023505"/>
				<field name="kind" value=""/>
			</field>
			<field name="alternateIdentifier">
				<field name="status" value="Application"/>
				<field name="format" value="docdb"/>
				<field name="country" value="BR"/>
				<field name="number" value="102014023505"/>
				<field name="kind" value="A"/>
			</field>
			<field name="alternateIdentifier">
				<field name="status" value="Application"/>
				<field name="format" value="epodoc"/>
				<field name="country" value="BR"/>
				<field name="number" value="BR20141023505"/>
				<field name="kind" value=""/>
			</field>
			<field name="alternateIdentifier">
				<field name="status" value="Application"/>
				<field name="format" value="original"/>
				<field name="country" value=""/>
				<field name="number" value="102014023505"/>
				<field name="kind" value=""/>
			</field>
		</entity>
		<entity ref="Person30210" type="Person">
			<semanticIdentifier>lattes::9443243894564249</semanticIdentifier>
			<field name="identifier.lattes" value="9443243894564249"/>
			<field name="name" value="Valdecir Angelo Quarcioni"/>
		</entity>
	</entities>
	<relations>
		<relation fromEntityRef="Patent44193" toEntityRef="Person30210" type="Inventor"/>
	</relations>
</entity-relation-data>
