<?xml version="1.0" encoding="ISO-8859-1"?>
<entity-relation-data lastUpdate="2023-03-27 16:25:32" record="12117" source="Espacenet">
	<entities>
		<entity ref="Patent12117" type="Patent">
			<semanticIdentifier>brcris::7edeb65235d7bd98da5566addc10c4d7</semanticIdentifier>
			<semanticIdentifier>docdb::BR102013029529A2</semanticIdentifier>
			<semanticIdentifier>epodoc::BR102013029529</semanticIdentifier>
			<semanticIdentifier>docdb::BR102013029529A</semanticIdentifier>
			<semanticIdentifier>epodoc::BR20131029529</semanticIdentifier>
			<semanticIdentifier>original::102013029529</semanticIdentifier>
			<field name="urlEspacenet" value="https://worldwide.espacenet.com/patent/search?q=102013029529"/>
			<field name="identifier.lattes" value="3577200530668581"/>
			<field name="identifier.espacenet" value="102013029529"/>
			<field name="kindCode" value="A2"/>
			<field name="title.espacenet" value="sistema e método de emissão de nota fiscal eletrônica ao consumidor"/>
			<field name="title.lattes" value="SISTEMA E MÉTODO DE EMISSÃO DE NOTA FISCAL ELETRÔNICA AO CONSUMIDOR"/>
			<field name="depositDate" value="2013-11-14"/>
			<field name="publicationDate" value="2015-09-08"/>
			<field name="countryCode" value="BR"/>
			<field name="inventor" value="ANDERSON LIMA"/>
			<field name="inventor" value="EDILSON FRESCHI"/>
			<field name="inventor" value="MARCELO FILIPAK"/>
			<field name="inventor" value="RAFAEL MOREIRA MIGGIORIN"/>
			<field name="inventor" value="REGGIE VIVEKANANDA"/>
			<field name="applicant" value="BEMATECH S.A"/>
			<field name="classification.ipc">
				<field name="sequence" value="1"/>
				<field name="text" value="G07G5/00AI"/>
				<field name="section" value="G"/>
				<field name="class" value="07"/>
				<field name="subclass" value="G"/>
				<field name="group" value="5"/>
				<field name="subgroup" value="00AI"/>
			</field>
			<field name="classification.ipc">
				<field name="sequence" value="2"/>
				<field name="text" value="G06Q30/06AI"/>
				<field name="section" value="G"/>
				<field name="class" value="06"/>
				<field name="subclass" value="Q"/>
				<field name="group" value="30"/>
				<field name="subgroup" value="06AI"/>
			</field>
			<field name="abstract.espacenet" value="sistema e método de emissão de nota fiscal eletrônica ao consumidor. o sistema de emissão de nota fiscal eletrônica ao consumidor compreende um módulo de ponto de venda de atuação com um programa aplicativo para interagir com um módulo de solução de emissão de nota fiscal eletrônica ao consumidor e para operar uma impressora emissora de cupom fiscal de acordo com as regras estabelecidas pela legislação fiscal; o módulo de solução de emissão nota fiscal eletrônica ao consumidor responsável pela interpretação do protocolo das regras das legislações, e conversão da informação recebida do módulo do ponto de venda no novo padrão definido para a emissão de nota fiscal eletrônica ao consumidor, dito módulo composto por emulador de impressora fiscal e gerenciador fiscal para geração, assinatura, emissão e custódia da nota fiscal eletrônica ao consumidor; e um módulo impressor não fiscal de impressão do documento fiscal auxiliar e de relatórios gerenciais gerados pelo gerenciador fiscal do módulo de solução de emissão nota fiscal eletrônica ao consumidor."/>
			<field name="originatesFrom" value="53056548"/>
			<field name="alternateIdentifier">
				<field name="status" value="Publication"/>
				<field name="format" value="docdb"/>
				<field name="country" value="BR"/>
				<field name="number" value="102013029529"/>
				<field name="kind" value="A2"/>
			</field>
			<field name="alternateIdentifier">
				<field name="status" value="Publication"/>
				<field name="format" value="epodoc"/>
				<field name="country" value="BR"/>
				<field name="number" value="BR102013029529"/>
				<field name="kind" value=""/>
			</field>
			<field name="alternateIdentifier">
				<field name="status" value="Application"/>
				<field name="format" value="docdb"/>
				<field name="country" value="BR"/>
				<field name="number" value="102013029529"/>
				<field name="kind" value="A"/>
			</field>
			<field name="alternateIdentifier">
				<field name="status" value="Application"/>
				<field name="format" value="epodoc"/>
				<field name="country" value="BR"/>
				<field name="number" value="BR20131029529"/>
				<field name="kind" value=""/>
			</field>
			<field name="alternateIdentifier">
				<field name="status" value="Application"/>
				<field name="format" value="original"/>
				<field name="country" value=""/>
				<field name="number" value="102013029529"/>
				<field name="kind" value=""/>
			</field>
			<field name="urlEspacenet" value="https://worldwide.espacenet.com/patent/search?q=WO2015070307"/>
		</entity>
		<entity ref="Person8350" type="Person">
			<semanticIdentifier>lattes::3577200530668581</semanticIdentifier>
			<field name="identifier.lattes" value="3577200530668581"/>
			<field name="name" value="Edilson José Freshi"/>
		</entity>
		<entity ref="Patent12118" type="Patent">
			<semanticIdentifier>epodoc::WO2015070307</semanticIdentifier>
			<field name="countryCode" value="WO"/>
			<field name="originatesFrom" value="53056548"/>
			<field name="alternateIdentifier">
				<field name="status" value="Publication"/>
				<field name="format" value="epodoc"/>
				<field name="country" value="WO"/>
				<field name="number" value="WO2015070307"/>
				<field name="kind" value=""/>
			</field>
		</entity>
	</entities>
	<relations>
		<relation fromEntityRef="Patent12117" toEntityRef="Person8350" type="Inventor"/>
	</relations>
</entity-relation-data>
