<?xml version="1.0" encoding="ISO-8859-1"?>
<entity-relation-data lastUpdate="2023-03-27 16:41:51" record="22012" source="Espacenet">
	<entities>
		<entity ref="Patent22012" type="Patent">
			<semanticIdentifier>brcris::5c02977bd9d4909297e1970ff0f3c17e</semanticIdentifier>
			<semanticIdentifier>docdb::BR102014011684A2</semanticIdentifier>
			<semanticIdentifier>epodoc::BR102014011684</semanticIdentifier>
			<semanticIdentifier>docdb::BR102014011684A</semanticIdentifier>
			<semanticIdentifier>epodoc::BR20141011684</semanticIdentifier>
			<semanticIdentifier>original::102014011684</semanticIdentifier>
			<field name="urlEspacenet" value="https://worldwide.espacenet.com/patent/search?q=102014011684"/>
			<field name="identifier.lattes" value="6775752719088891"/>
			<field name="identifier.espacenet" value="102014011684"/>
			<field name="kindCode" value="A2"/>
			<field name="title.espacenet" value="ladrilho hidráulico em camada única vibrado contendo resíduo de rocha ornamental proveniente do tear de fio diamantado"/>
			<field name="title.lattes" value="Ladrilho Hidráukico em Camada Única vibrado contendo resíduo de Rocha Ornamental Proveniente do Tear de Fio Diamantado"/>
			<field name="depositDate" value="2014-05-06"/>
			<field name="publicationDate" value="2016-05-24"/>
			<field name="countryCode" value="BR"/>
			<field name="inventor" value="ANDRE ZOTELLE DESTEFANI"/>
			<field name="inventor" value="JONAS ALEXANDRE"/>
			<field name="inventor" value="JOSE NILSON FRANCA DE HOLANDA"/>
			<field name="applicant" value="UENF-UNIVERSIDADE EST. DO NORTE FLUMINENSE DARCY RIBEIRO"/>
			<field name="classification.ipc">
				<field name="sequence" value="1"/>
				<field name="text" value="C04B7/24AI"/>
				<field name="section" value="C"/>
				<field name="class" value="04"/>
				<field name="subclass" value="B"/>
				<field name="group" value="7"/>
				<field name="subgroup" value="24AI"/>
			</field>
			<field name="classification.ipc">
				<field name="sequence" value="2"/>
				<field name="text" value="C04B28/02AI"/>
				<field name="section" value="C"/>
				<field name="class" value="04"/>
				<field name="subclass" value="B"/>
				<field name="group" value="28"/>
				<field name="subgroup" value="02AI"/>
			</field>
			<field name="abstract.espacenet" value="ladrilho hidráulico em camada única vibrado contendo resíduo de rocha ornamental proveniente do tear de fio diamantado - a presente patente refere-se a um modelo de ladrilho hidráulico em camada única vibrado que incorpora resíduo de rocha ornamental proveniente do tear de fio diamantado, para uso na construção civil para pavimentação. a nova composição de ladrilhos hidráulicos, proposta nesta patente, apresenta resíduos de rocha ornamental provenientes do tear de fio diamantado correspondendo a 20% da massa total dos agregados incorporados à massa cerâmica. adicionalmente, a preparação desse ladrilho hidráulico envolve, além do uso de matérias-primas não usuais, o desenvolvimento de uma camada única com características adequadas de granulometria e mistura entre as matérias-prim as, de partida, que favorecem a operação de conformação por vibração mecânica para confecção do ladrilho hidráulico."/>
			<field name="originatesFrom" value="56012707"/>
			<field name="alternateIdentifier">
				<field name="status" value="Publication"/>
				<field name="format" value="docdb"/>
				<field name="country" value="BR"/>
				<field name="number" value="102014011684"/>
				<field name="kind" value="A2"/>
			</field>
			<field name="alternateIdentifier">
				<field name="status" value="Publication"/>
				<field name="format" value="epodoc"/>
				<field name="country" value="BR"/>
				<field name="number" value="BR102014011684"/>
				<field name="kind" value=""/>
			</field>
			<field name="alternateIdentifier">
				<field name="status" value="Application"/>
				<field name="format" value="docdb"/>
				<field name="country" value="BR"/>
				<field name="number" value="102014011684"/>
				<field name="kind" value="A"/>
			</field>
			<field name="alternateIdentifier">
				<field name="status" value="Application"/>
				<field name="format" value="epodoc"/>
				<field name="country" value="BR"/>
				<field name="number" value="BR20141011684"/>
				<field name="kind" value=""/>
			</field>
			<field name="alternateIdentifier">
				<field name="status" value="Application"/>
				<field name="format" value="original"/>
				<field name="country" value=""/>
				<field name="number" value="102014011684"/>
				<field name="kind" value=""/>
			</field>
		</entity>
		<entity ref="Person15221" type="Person">
			<semanticIdentifier>lattes::6775752719088891</semanticIdentifier>
			<field name="identifier.lattes" value="6775752719088891"/>
			<field name="name" value="Jonas Alexandre"/>
		</entity>
	</entities>
	<relations>
		<relation fromEntityRef="Patent22012" toEntityRef="Person15221" type="Inventor"/>
	</relations>
</entity-relation-data>
