<?xml version="1.0" encoding="ISO-8859-1"?>
<entity-relation-data lastUpdate="2023-03-27 16:07:47" record="1590" source="Espacenet">
	<entities>
		<entity ref="Patent1590" type="Patent">
			<semanticIdentifier>brcris::2f1e85214e74c45ac8038490489ce29f</semanticIdentifier>
			<semanticIdentifier>docdb::BRPI0400495A</semanticIdentifier>
			<semanticIdentifier>epodoc::BRPI0400495</semanticIdentifier>
			<semanticIdentifier>docdb::BRPI0400495A</semanticIdentifier>
			<semanticIdentifier>epodoc::BR2004PI00495</semanticIdentifier>
			<semanticIdentifier>original::0400495-7</semanticIdentifier>
			<field name="urlEspacenet" value="https://worldwide.espacenet.com/patent/search?q=PI0400495"/>
			<field name="identifier.lattes" value="0353068309348963"/>
			<field name="identifier.espacenet" value="PI0400495"/>
			<field name="kindCode" value="A"/>
			<field name="title.espacenet" value="Equipamento e método para conversão de fornos elétricos para gás natural ou glp"/>
			<field name="title.lattes" value="Equipamento e Método para conversão de fornos elétricos para gás natural ou GLP"/>
			<field name="depositDate" value="2004-02-11"/>
			<field name="publicationDate" value="2005-09-27"/>
			<field name="countryCode" value="BR"/>
			<field name="inventor" value="ALEXANDRE KUPKA DA SILVA"/>
			<field name="inventor" value="HENRIQUE GERKEN DE LANDA"/>
			<field name="inventor" value="MARCIA BARBOSA HENRIQUES MATELLI"/>
			<field name="applicant" value="PETROLEO BRASILEIRO S.A. - PETROBRAS"/>
			<field name="classification.ipc">
				<field name="sequence" value="1"/>
				<field name="text" value="F27D1/00AI"/>
				<field name="section" value="F"/>
				<field name="class" value="27"/>
				<field name="subclass" value="D"/>
				<field name="group" value="1"/>
				<field name="subgroup" value="00AI"/>
			</field>
			<field name="classification.ipc">
				<field name="sequence" value="2"/>
				<field name="text" value="A21B1/26AI"/>
				<field name="section" value="A"/>
				<field name="class" value="21"/>
				<field name="subclass" value="B"/>
				<field name="group" value="1"/>
				<field name="subgroup" value="26AI"/>
			</field>
			<field name="abstract.espacenet" value="&quot;EQUIPAMENTO E MéTODO PARA CONVERSãO DE FORNOS ELéTRICOS PARA GáS NATURAL OU GLP&quot;. A invenção diz respeito a um equipamento e método para conversão de fornos elétricos que promovem o aquecimento do ar na câmara de cocção por intermédio de resistências elétricas, para gás natural ou GLP, compreendendo: Uma pluralidade de estruturas tubulares metálicas (1), fechadas a vácuo, as quais apresentam uma porção inclinada (2) e uma porção reta (3), tais porções isoladas adiabaticamente entre si. A pluralidade de estruturas tubulares metálicas descritas é preenchida total ou em parte com um fluido de trabalho a ser evaporado, por meio da colocação de queimadores (13) sob a porção inclinada (2) da dita estrutura tubular (1), de modo que o calor gerado pela evaporação do fluido de trabalho e também pela combustão do gás seja aproveitado para o aquecimento da câmara de cocção (6) do forno."/>
			<field name="originatesFrom" value="35044316"/>
			<field name="alternateIdentifier">
				<field name="status" value="Publication"/>
				<field name="format" value="docdb"/>
				<field name="country" value="BR"/>
				<field name="number" value="PI0400495"/>
				<field name="kind" value="A"/>
			</field>
			<field name="alternateIdentifier">
				<field name="status" value="Publication"/>
				<field name="format" value="epodoc"/>
				<field name="country" value="BR"/>
				<field name="number" value="BRPI0400495"/>
				<field name="kind" value=""/>
			</field>
			<field name="alternateIdentifier">
				<field name="status" value="Application"/>
				<field name="format" value="docdb"/>
				<field name="country" value="BR"/>
				<field name="number" value="PI0400495"/>
				<field name="kind" value="A"/>
			</field>
			<field name="alternateIdentifier">
				<field name="status" value="Application"/>
				<field name="format" value="epodoc"/>
				<field name="country" value="BR"/>
				<field name="number" value="BR2004PI00495"/>
				<field name="kind" value=""/>
			</field>
			<field name="alternateIdentifier">
				<field name="status" value="Application"/>
				<field name="format" value="original"/>
				<field name="country" value=""/>
				<field name="number" value="0400495-7"/>
				<field name="kind" value=""/>
			</field>
		</entity>
		<entity ref="Person1183" type="Person">
			<semanticIdentifier>lattes::0353068309348963</semanticIdentifier>
			<field name="identifier.lattes" value="0353068309348963"/>
			<field name="name" value="Alexandre Kupka da Silva"/>
		</entity>
		<entity ref="OrgUnit910" type="OrgUnit">
			<semanticIdentifier>brcris::bcc892d0b77dad2b257c5474437ac458</semanticIdentifier>
			<field name="name" value="PETROLEO BRASILEIRO S.A. - PETROBRAS"/>
		</entity>
	</entities>
	<relations>
		<relation fromEntityRef="Patent1590" toEntityRef="Person1183" type="Inventor"/>
		<relation fromEntityRef="Patent1590" toEntityRef="OrgUnit910" type="Applicant"/>
	</relations>
</entity-relation-data>
